{"cameraMode":{"drawMode":0,"name":"Shaded","section":"Shading Mode"},"sceneLighting":true,"audioPlay":false,"sceneViewState":{"m_AlwaysRefresh":false,"showFog":true,"showSkybox":true,"showFlares":true,"showImageEffects":true,"showParticleSystems":true,"showVisualEffectGraphs":true,"m_FxEnabled":true},"in2DMode":false,"pivot":{"x":2.291518449783325,"y":-26.4027042388916,"z":26.079980850219728},"rotation":{"x":0.35376816987991335,"y":0.6283100843429565,"z":-0.3864347040653229,"w":0.5751773715019226},"size":40.93545150756836,"orthographic":false}